psi_continuum_v2/__init__.py
psi_continuum_v2/check_data.py
psi_continuum_v2/analysis/__init__.py
psi_continuum_v2/analysis/check/__init__.py
psi_continuum_v2/analysis/check/check_bao_dr12_data.py
psi_continuum_v2/analysis/check/check_desi_dr2_data.py
psi_continuum_v2/analysis/check/check_hz_data.py
psi_continuum_v2/analysis/check/check_models.py
psi_continuum_v2/analysis/check/check_pantheonplus_data.py
psi_continuum_v2/analysis/pipeline/__init__.py
psi_continuum_v2/analysis/pipeline/joint_fit_psicdm.py
psi_continuum_v2/analysis/plots/__init__.py
psi_continuum_v2/analysis/plots/make_publication_plots.py
psi_continuum_v2/analysis/scans/__init__.py
psi_continuum_v2/analysis/scans/scan_eps_psicdm.py
psi_continuum_v2/analysis/styles/__init__.py
psi_continuum_v2/analysis/styles/psi_style.mplstyle
psi_continuum_v2/analysis/tests/__init__.py
psi_continuum_v2/analysis/tests/bao_desi_dr2_test.py
psi_continuum_v2/analysis/tests/eps_best_joint_test.py
psi_continuum_v2/analysis/tests/hz_test_psicdm.py
psi_continuum_v2/analysis/tests/sn_test_lcdm_pplus_simple.py
psi_continuum_v2/analysis/tests/sn_test_psicdm_pplus.py
psi_continuum_v2/cli/__init__.py
psi_continuum_v2/cli/menu.py
psi_continuum_v2/cli/run_all.py
psi_continuum_v2/cosmology/__init__.py
psi_continuum_v2/cosmology/constants.py
psi_continuum_v2/cosmology/background/__init__.py
psi_continuum_v2/cosmology/background/distances.py
psi_continuum_v2/cosmology/background/lcdm.py
psi_continuum_v2/cosmology/background/psicdm.py
psi_continuum_v2/cosmology/data_loaders/__init__.py
psi_continuum_v2/cosmology/data_loaders/bao_loader.py
psi_continuum_v2/cosmology/data_loaders/covariance_loader.py
psi_continuum_v2/cosmology/data_loaders/desi_loader.py
psi_continuum_v2/cosmology/data_loaders/hz_loader.py
psi_continuum_v2/cosmology/data_loaders/pantheonplus_loader.py
psi_continuum_v2/cosmology/data_loaders/validators.py
psi_continuum_v2/cosmology/likelihoods/__init__.py
psi_continuum_v2/cosmology/likelihoods/bao_likelihood.py
psi_continuum_v2-0.2.3.dist-info/licenses/LICENSE
psi_continuum_v2-0.2.3.dist-info/METADATA
psi_continuum_v2-0.2.3.dist-info/WHEEL
psi_continuum_v2-0.2.3.dist-info/entry_points.txt
psi_continuum_v2-0.2.3.dist-info/top_level.txt
psi_continuum_v2-0.2.3.dist-info/RECORD
