Metadata-Version: 2.4
Name: psi-continuum-v2
Version: 0.2.3
Summary: Psi-Continuum v2: cosmological framework and joint likelihood analysis for the Psi-CDM model.
Author-email: "Dmitry V. Klimov" <d.klimov.psi@gmail.com>
License: MIT
Project-URL: Homepage, https://github.com/dmitrylife/psi-continuum-v2
Project-URL: Documentation, https://psi-continuum.org/docs/v2
Project-URL: Source, https://github.com/dmitrylife/psi-continuum-v2
Project-URL: Issues, https://github.com/dmitrylife/psi-continuum-v2/issues
Keywords: cosmology,psi-continuum,lcdm,dark-energy,supernovae,bao,desi,pantheon,astrophysics
Classifier: Development Status :: 5 - Production/Stable
Classifier: Intended Audience :: Science/Research
Classifier: License :: OSI Approved :: MIT License
Classifier: Programming Language :: Python :: 3
Classifier: Programming Language :: Python :: 3.10
Classifier: Programming Language :: Python :: 3.11
Classifier: Programming Language :: Python :: 3.12
Classifier: Programming Language :: Python :: 3.13
Classifier: Topic :: Scientific/Engineering :: Astronomy
Classifier: Topic :: Scientific/Engineering :: Physics
Classifier: Topic :: Scientific/Engineering :: Information Analysis
Classifier: Operating System :: OS Independent
Requires-Python: >=3.10
License-File: LICENSE
Requires-Dist: numpy>=1.23
Requires-Dist: scipy>=1.9
Requires-Dist: matplotlib>=3.6
Provides-Extra: test
Requires-Dist: pytest; extra == "test"
Dynamic: license-file
